{
  "display": {
    "in_func_code": "5 ",
    "in_boro": "4",
    "in_high_house_number": "200             ",
    "in_low_house_number": "100             ",
    "in_stname": "HILLSIDE AVE                    ",
    "in_b10sc1": "4          ",
    "out_grc": "00",
    "out_error_message": "                                                                                ",
    "out_high_grid_key": "014496902000200000AA ",
    "out_low_grid_key": "000100000AA",
    "out_stame": "HILLSIDE AVENUE                 "
  },
  "root": null
}