{
  "display": null,
  "root": {
    "wa1": {
      "in_func_code": "1A",
      "in_hnd": "90-15           ",
      "in_hns": "           ",
      "in_low_hnd": "                ",
      "in_low_hns": "           ",
      "in_b10sc1": {
        "boro": "4",
        "sc5": "     ",
        "lgc": "  ",
        "spv": "   "
      },
      "in_boro1": "4",
      "in_boro2": " ",
      "in_boro3": " ",
      "in_stname1": "QUEENS BLVD                     ",
      "in_b10sc2": {
        "boro": " ",
        "sc5": "     ",
        "lgc": "  ",
        "spv": "   "
      },
      "in_stname2": "                                ",
      "in_b10sc3": {
        "boro": " ",
        "sc5": "     ",
        "lgc": "  ",
        "spv": "   "
      },
      "in_stname3": "                                ",
      "in_bbl": {
        "boro": " ",
        "block": "     ",
        "lot": "    "
      },
      "in_filler01": " ",
      "in_bin": {
        "boro": " ",
        "binnum": "      "
      },
      "in_bin_string": "       ",
      "in_compass_dir": " ",
      "in_compass_dir2": " ",
      "in_node": "       ",
      "in_platform_ind": "C",
      "in_zip_code": "11373",
      "in_unit": "Z2            ",
      "in_filler03": "                                                                                  ",
      "in_long_wa2_flag": " ",
      "in_hn_justification": " ",
      "in_hnl": "  ",
      "in_hn_norm_override": " ",
      "in_snl": "  ",
      "in_stname_normalization": " ",
      "in_xstreet_names_flag": " ",
      "in_roadbed_request_switch": " ",
      "in_legacy_grc_flag": " ",
      "in_auxseg_switch": " ",
      "in_browse_flag": " ",
      "in_real_street_only": " ",
      "in_tpad_switch": " ",
      "in_mode_switch": "X",
      "in_filler4": "                              ",
      "out_boro_name1": "QUEENS   ",
      "out_hnd": "90-15           ",
      "out_hns": "100090015AA",
      "out_b10sc1": {
        "boro": "4",
        "sc5": "59990",
        "lgc": "01",
        "spv": "010"
      },
      "out_stname1": "QUEENS BOULEVARD                ",
      "out_b10sc2": {
        "boro": " ",
        "sc5": "     ",
        "lgc": "  ",
        "spv": "   "
      },
      "out_stname2": "                                ",
      "out_b10sc3": {
        "boro": " ",
        "sc5": "     ",
        "lgc": "  ",
        "spv": "   "
      },
      "out_stname3": "                                ",
      "out_bbl": {
        "boro": " ",
        "block": "     ",
        "lot": "    "
      },
      "out_filler02": " ",
      "out_low_hnd": "                ",
      "out_low_hns": "           ",
      "out_bin": {
        "boro": " ",
        "binnum": "      "
      },
      "out_attr_bytes": [
        "M",
        " ",
        " "
      ],
      "out_reason_code2": " ",
      "out_reason_code_qualifier2": " ",
      "out_warning_code2": "  ",
      "out_grc2": "  ",
      "out_error_message2": "                                                                                ",
      "out_node": "       ",
      "out_units": {
        "unit_type": "#   ",
        "unit_identifier": "Z    2    "
      },
      "out_unit": "# Z2          ",
      "out_filler03": "                 ",
      "out_st_attr": "M",
      "out_reason_code": " ",
      "out_reason_code_qualifier": " ",
      "out_warning_code": "  ",
      "out_grc": "00",
      "out_error_message": "                                                                                ",
      "out_number_of_stcodes": "  ",
      "out_b7sc_list": [
        {
          "boro": " ",
          "sc5": "     ",
          "lgc": "  "
        },
        {
          "boro": " ",
          "sc5": "     ",
          "lgc": "  "
        },
        {
          "boro": " ",
          "sc5": "     ",
          "lgc": "  "
        },
        {
          "boro": " ",
          "sc5": "     ",
          "lgc": "  "
        },
        {
          "boro": " ",
          "sc5": "     ",
          "lgc": "  "
        },
        {
          "boro": " ",
          "sc5": "     ",
          "lgc": "  "
        },
        {
          "boro": " ",
          "sc5": "     ",
          "lgc": "  "
        },
        {
          "boro": " ",
          "sc5": "     ",
          "lgc": "  "
        },
        {
          "boro": " ",
          "sc5": "     ",
          "lgc": "  "
        },
        {
          "boro": " ",
          "sc5": "     ",
          "lgc": "  "
        }
      ],
      "out_stname_list": [
        "                                ",
        "                                ",
        "                                ",
        "                                ",
        "                                ",
        "                                ",
        "                                ",
        "                                ",
        "                                ",
        "                                "
      ]
    },
    "wa2f1ax": {
      "gridkey1": {
        "record_type": "01",
        "b5sc": {
          "boro": "4",
          "sc5": "59990"
        },
        "parity": "1",
        "hi_hns": "100090025AA",
        "filler": " "
      },
      "cont_parity_ind": " ",
      "lohns": "100090015AA",
      "bbl": {
        "boro": "4",
        "block": "01860",
        "lot": "0100"
      },
      "filler1": " ",
      "rpad_scc": "4",
      "filler2": " ",
      "rpad_bldg_class": "K6",
      "corner_code": "CR",
      "num_of_bldgs": "0001",
      "num_of_blockfaces": "05",
      "interior_flag": " ",
      "vacant_flag": " ",
      "irreg_flag": "I",
      "mh_ri_flag": " ",
      "addr_overflow_flag": " ",
      "stroll_key": "                   ",
      "res_internal_use": " ",
      "bin": {
        "boro": "4",
        "binnum": "045999"
      },
      "condo_flag": " ",
      "filler3": " ",
      "condo_num": "    ",
      "filler4": "       ",
      "condo_bill_bbl": {
        "boro": "0",
        "block": "00000",
        "lot": "0000"
      },
      "filler5": " ",
      "condo_bill_scc": " ",
      "condo_lo_bbl": {
        "boro": "4",
        "block": "01860",
        "lot": "0100"
      },
      "filler6": " ",
      "condo_hi_bbl": {
        "boro": "4",
        "block": "01860",
        "lot": "0100"
      },
      "filler7": " ",
      "condo_base_bbl": {
        "boro": " ",
        "block": "     ",
        "lot": "    "
      },
      "filler8": "     ",
      "coop_num": "0000",
      "sanborn": {
        "boro": "4",
        "volume": "19",
        "volume_suffix": " ",
        "page": "087",
        "page_suffix": " "
      },
      "business_area": {
        "boro": "4",
        "district_number": "2002"
      },
      "dof_map": {
        "boro": "4",
        "section_volume": "1101",
        "page": "    "
      },
      "filler9": "   ",
      "latitude": "40.734566",
      "longitude": "-73.870652 ",
      "x_coord": "1020097",
      "y_coord": "0206925",
      "bid_id": {
        "boro": " ",
        "sc5": "     "
      },
      "TPAD_bin_status": " ",
      "TPAD_new_bin": {
        "boro": " ",
        "binnum": "      "
      },
      "TPAD_new_bin_status": " ",
      "TPAD_conflict_flag": " ",
      "DCP_Zoning_Map": "13C",
      "filler10": "      ",
      "valid_lgcs": [
        "01",
        "  ",
        "  ",
        "  "
      ],
      "reason_code": " ",
      "reason_code_qualifier": " ",
      "warning_code": "  ",
      "grc": "00",
      "filler11": "                                                                                                            ",
      "num_of_addrs": "0007",
      "addr_x_list": [
        {
          "lhnd": "           90-15",
          "hhnd": "           90-25",
          "b7sc": {
            "boro": "4",
            "sc5": "59990",
            "lgc": "01"
          },
          "bin": {
            "boro": "4",
            "binnum": "045999"
          },
          "sos": "L",
          "addr_type": " ",
          "TPAD_bin_status": " ",
          "stname": "QUEENS BOULEVARD                ",
          "filler01": "                                  "
        },
        {
          "lhnd": "           90-02",
          "hhnd": "           90-02",
          "b7sc": {
            "boro": "4",
            "sc5": "11840",
            "lgc": "01"
          },
          "bin": {
            "boro": "4",
            "binnum": "045999"
          },
          "sos": "R",
          "addr_type": " ",
          "TPAD_bin_status": " ",
          "stname": "  57 AVENUE                     ",
          "filler01": "                                  "
        },
        {
          "lhnd": "           91-05",
          "hhnd": "           91-05",
          "b7sc": {
            "boro": "4",
            "sc5": "12240",
            "lgc": "01"
          },
          "bin": {
            "boro": "4",
            "binnum": "045999"
          },
          "sos": "L",
          "addr_type": " ",
          "TPAD_bin_status": " ",
          "stname": "  59 AVENUE                     ",
          "filler01": "                                  "
        },
        {
          "lhnd": "                ",
          "hhnd": "                ",
          "b7sc": {
            "boro": "4",
            "sc5": "15785",
            "lgc": "01"
          },
          "bin": {
            "boro": "4",
            "binnum": "045999"
          },
          "sos": "L",
          "addr_type": "N",
          "TPAD_bin_status": " ",
          "stname": "QUEENS CENTER MALL              ",
          "filler01": "                                  "
        },
        {
          "lhnd": "           57-01",
          "hhnd": "           57-01",
          "b7sc": {
            "boro": "4",
            "sc5": "18240",
            "lgc": "01"
          },
          "bin": {
            "boro": "4",
            "binnum": "045999"
          },
          "sos": "L",
          "addr_type": " ",
          "TPAD_bin_status": " ",
          "stname": "  90 STREET                     ",
          "filler01": "                                  "
        },
        {
          "lhnd": "           57-02",
          "hhnd": "           57-02",
          "b7sc": {
            "boro": "4",
            "sc5": "18490",
            "lgc": "01"
          },
          "bin": {
            "boro": "4",
            "binnum": "045999"
          },
          "sos": "R",
          "addr_type": " ",
          "TPAD_bin_status": " ",
          "stname": "  92 STREET                     ",
          "filler01": "                                  "
        },
        {
          "lhnd": "           90-01",
          "hhnd": "           90-03",
          "b7sc": {
            "boro": "4",
            "sc5": "59990",
            "lgc": "01"
          },
          "bin": {
            "boro": "4",
            "binnum": "045999"
          },
          "sos": "L",
          "addr_type": " ",
          "TPAD_bin_status": " ",
          "stname": "QUEENS BOULEVARD                ",
          "filler01": "                                  "
        },
        {
          "lhnd": "                ",
          "hhnd": "                ",
          "b7sc": {
            "boro": " ",
            "sc5": "     ",
            "lgc": "  "
          },
          "bin": {
            "boro": " ",
            "binnum": "      "
          },
          "sos": " ",
          "addr_type": " ",
          "TPAD_bin_status": " ",
          "stname": "                                ",
          "filler01": "                                  "
        },
        {
          "lhnd": "                ",
          "hhnd": "                ",
          "b7sc": {
            "boro": " ",
            "sc5": "     ",
            "lgc": "  "
          },
          "bin": {
            "boro": " ",
            "binnum": "      "
          },
          "sos": " ",
          "addr_type": " ",
          "TPAD_bin_status": " ",
          "stname": "                                ",
          "filler01": "                                  "
        },
        {
          "lhnd": "                ",
          "hhnd": "                ",
          "b7sc": {
            "boro": " ",
            "sc5": "     ",
            "lgc": "  "
          },
          "bin": {
            "boro": " ",
            "binnum": "      "
          },
          "sos": " ",
          "addr_type": " ",
          "TPAD_bin_status": " ",
          "stname": "                                ",
          "filler01": "                                  "
        },
        {
          "lhnd": "                ",
          "hhnd": "                ",
          "b7sc": {
            "boro": " ",
            "sc5": "     ",
            "lgc": "  "
          },
          "bin": {
            "boro": " ",
            "binnum": "      "
          },
          "sos": " ",
          "addr_type": " ",
          "TPAD_bin_status": " ",
          "stname": "                                ",
          "filler01": "                                  "
        },
        {
          "lhnd": "                ",
          "hhnd": "                ",
          "b7sc": {
            "boro": " ",
            "sc5": "     ",
            "lgc": "  "
          },
          "bin": {
            "boro": " ",
            "binnum": "      "
          },
          "sos": " ",
          "addr_type": " ",
          "TPAD_bin_status": " ",
          "stname": "                                ",
          "filler01": "                                  "
        },
        {
          "lhnd": "                ",
          "hhnd": "                ",
          "b7sc": {
            "boro": " ",
            "sc5": "     ",
            "lgc": "  "
          },
          "bin": {
            "boro": " ",
            "binnum": "      "
          },
          "sos": " ",
          "addr_type": " ",
          "TPAD_bin_status": " ",
          "stname": "                                ",
          "filler01": "                                  "
        },
        {
          "lhnd": "                ",
          "hhnd": "                ",
          "b7sc": {
            "boro": " ",
            "sc5": "     ",
            "lgc": "  "
          },
          "bin": {
            "boro": " ",
            "binnum": "      "
          },
          "sos": " ",
          "addr_type": " ",
          "TPAD_bin_status": " ",
          "stname": "                                ",
          "filler01": "                                  "
        },
        {
          "lhnd": "                ",
          "hhnd": "                ",
          "b7sc": {
            "boro": " ",
            "sc5": "     ",
            "lgc": "  "
          },
          "bin": {
            "boro": " ",
            "binnum": "      "
          },
          "sos": " ",
          "addr_type": " ",
          "TPAD_bin_status": " ",
          "stname": "                                ",
          "filler01": "                                  "
        },
        {
          "lhnd": "                ",
          "hhnd": "                ",
          "b7sc": {
            "boro": " ",
            "sc5": "     ",
            "lgc": "  "
          },
          "bin": {
            "boro": " ",
            "binnum": "      "
          },
          "sos": " ",
          "addr_type": " ",
          "TPAD_bin_status": " ",
          "stname": "                                ",
          "filler01": "                                  "
        },
        {
          "lhnd": "                ",
          "hhnd": "                ",
          "b7sc": {
            "boro": " ",
            "sc5": "     ",
            "lgc": "  "
          },
          "bin": {
            "boro": " ",
            "binnum": "      "
          },
          "sos": " ",
          "addr_type": " ",
          "TPAD_bin_status": " ",
          "stname": "                                ",
          "filler01": "                                  "
        },
        {
          "lhnd": "                ",
          "hhnd": "                ",
          "b7sc": {
            "boro": " ",
            "sc5": "     ",
            "lgc": "  "
          },
          "bin": {
            "boro": " ",
            "binnum": "      "
          },
          "sos": " ",
          "addr_type": " ",
          "TPAD_bin_status": " ",
          "stname": "                                ",
          "filler01": "                                  "
        },
        {
          "lhnd": "                ",
          "hhnd": "                ",
          "b7sc": {
            "boro": " ",
            "sc5": "     ",
            "lgc": "  "
          },
          "bin": {
            "boro": " ",
            "binnum": "      "
          },
          "sos": " ",
          "addr_type": " ",
          "TPAD_bin_status": " ",
          "stname": "                                ",
          "filler01": "                                  "
        },
        {
          "lhnd": "                ",
          "hhnd": "                ",
          "b7sc": {
            "boro": " ",
            "sc5": "     ",
            "lgc": "  "
          },
          "bin": {
            "boro": " ",
            "binnum": "      "
          },
          "sos": " ",
          "addr_type": " ",
          "TPAD_bin_status": " ",
          "stname": "                                ",
          "filler01": "                                  "
        },
        {
          "lhnd": "                ",
          "hhnd": "                ",
          "b7sc": {
            "boro": " ",
            "sc5": "     ",
            "lgc": "  "
          },
          "bin": {
            "boro": " ",
            "binnum": "      "
          },
          "sos": " ",
          "addr_type": " ",
          "TPAD_bin_status": " ",
          "stname": "                                ",
          "filler01": "                                  "
        }
      ]
    },
    "AddressRangeList": [
      {
        "type": " ",
        "type_meaning": "Ordinary Address Range",
        "low_address_number": "           90-15",
        "high_address_number": "           90-25",
        "street_name": "QUEENS BOULEVARD                ",
        "bin": "4045999",
        "tpad_bin_status": "N/A",
        "b7sc": "45999001"
      },
      {
        "type": " ",
        "type_meaning": "Ordinary Address Range",
        "low_address_number": "           90-02",
        "high_address_number": "           90-02",
        "street_name": "  57 AVENUE                     ",
        "bin": "4045999",
        "tpad_bin_status": "N/A",
        "b7sc": "41184001"
      },
      {
        "type": " ",
        "type_meaning": "Ordinary Address Range",
        "low_address_number": "           91-05",
        "high_address_number": "           91-05",
        "street_name": "  59 AVENUE                     ",
        "bin": "4045999",
        "tpad_bin_status": "N/A",
        "b7sc": "41224001"
      },
      {
        "type": "N",
        "type_meaning": "Non-Addressable Place Name",
        "low_address_number": "                ",
        "high_address_number": "                ",
        "street_name": "QUEENS CENTER MALL              ",
        "bin": "4045999",
        "tpad_bin_status": "N/A",
        "b7sc": "41578501"
      },
      {
        "type": " ",
        "type_meaning": "Ordinary Address Range",
        "low_address_number": "           57-01",
        "high_address_number": "           57-01",
        "street_name": "  90 STREET                     ",
        "bin": "4045999",
        "tpad_bin_status": "N/A",
        "b7sc": "41824001"
      },
      {
        "type": " ",
        "type_meaning": "Ordinary Address Range",
        "low_address_number": "           57-02",
        "high_address_number": "           57-02",
        "street_name": "  92 STREET                     ",
        "bin": "4045999",
        "tpad_bin_status": "N/A",
        "b7sc": "41849001"
      },
      {
        "type": " ",
        "type_meaning": "Ordinary Address Range",
        "low_address_number": "           90-01",
        "high_address_number": "           90-03",
        "street_name": "QUEENS BOULEVARD                ",
        "bin": "4045999",
        "tpad_bin_status": "N/A",
        "b7sc": "45999001"
      }
    ],
    "CompleteBINList": [
      {
        "bin": "4045999",
        "tpad": null
      }
    ],
    "out_bin_toString": "4045999",
    "out_bbl_toString": "4018600100",
    "out_b10sc_toString": "45999001010",
    "out_business_area_toString": "42002",
    "out_bid_toString": "      ",
    "out_dof_map_toString": "41101    ",
    "out_sanborn_toString": "419 087 "
  }
}